quartodoc/__init__.py
quartodoc/__main__.py
quartodoc/_pydantic_compat.py
quartodoc/ast.py
quartodoc/autosummary.py
quartodoc/interlinks.py
quartodoc/inventory.py
quartodoc/layout.py
quartodoc/parsers.py
quartodoc/validation.py
quartodoc/_griffe_compat/__init__.py
quartodoc/_griffe_compat/_generate_stubs.py
quartodoc/_griffe_compat/dataclasses.py
quartodoc/_griffe_compat/docstrings.py
quartodoc/_griffe_compat/expressions.py
quartodoc/builder/__init__.py
quartodoc/builder/_node.py
quartodoc/builder/blueprint.py
quartodoc/builder/collect.py
quartodoc/builder/utils.py
quartodoc/builder/write.py
quartodoc/pandoc/__init__.py
quartodoc/pandoc/blocks.py
quartodoc/pandoc/components.py
quartodoc/pandoc/inlines.py
quartodoc/renderers/__init__.py
quartodoc/renderers/base.py
quartodoc/renderers/md_renderer.py
quartodoc/static/styles.css
quartodoc/tests/__init__.py
quartodoc/tests/example.py
quartodoc/tests/example_alias_target.py
quartodoc/tests/example_alias_target__nested.py
quartodoc/tests/example_attribute.py
quartodoc/tests/example_class.py
quartodoc/tests/example_docstring_styles.py
quartodoc/tests/example_dynamic.py
quartodoc/tests/example_signature.py
quartodoc/tests/example_star_imports.py
quartodoc/tests/example_stubs.py
quartodoc/tests/example_stubs.pyi
quartodoc/tests/test_ast.py
quartodoc/tests/test_basic.py
quartodoc/tests/test_builder.py
quartodoc/tests/test_builder_blueprint.py
quartodoc/tests/test_cli.py
quartodoc/tests/test_interlinks.py
quartodoc/tests/test_layout.py
quartodoc/tests/test_renderers.py
quartodoc/tests/test_validation.py
quartodoc/tests/__snapshots__/test_builder.ambr
quartodoc/tests/__snapshots__/test_renderers.ambr
quartodoc/tests/__snapshots__/test_validation.ambr
quartodoc/tests/example_interlinks/.gitignore
quartodoc/tests/example_interlinks/README.md
quartodoc/tests/example_interlinks/_quarto.yml
quartodoc/tests/example_interlinks/interlinks.lua
quartodoc/tests/example_interlinks/objects.json
quartodoc/tests/example_interlinks/spec.yml
quartodoc-0.11.1.dist-info/licenses/LICENSE
quartodoc-0.11.1.dist-info/METADATA
quartodoc-0.11.1.dist-info/WHEEL
quartodoc-0.11.1.dist-info/entry_points.txt
quartodoc-0.11.1.dist-info/top_level.txt
quartodoc-0.11.1.dist-info/RECORD
