Metadata-Version: 2.4
Name: quartodoc
Version: 0.11.1
Summary: Generate API documentation with Quarto.
Author-email: Michael Chow <michael.chow@posit.co>
License: MIT License
Project-URL: homepage, https://machow.github.io/quartodoc
Project-URL: repository, https://github.com/machow/quartodoc
Project-URL: ci, https://github.com/machow/quartodoc/actions
Keywords: documentation,quarto
Classifier: License :: OSI Approved :: MIT License
Classifier: Operating System :: Microsoft :: Windows
Classifier: Operating System :: Unix
Classifier: Operating System :: MacOS
Classifier: Programming Language :: Python :: 3 :: Only
Classifier: Programming Language :: Python :: 3.9
Classifier: Programming Language :: Python :: 3.10
Classifier: Programming Language :: Python :: 3.11
Requires-Python: >=3.9
License-File: LICENSE
Requires-Dist: black
Requires-Dist: click
Requires-Dist: griffe>=0.33
Requires-Dist: sphobjinv>=2.3.1
Requires-Dist: tabulate>=0.9.0
Requires-Dist: importlib-metadata>=5.1.0
Requires-Dist: importlib-resources>=5.10.2
Requires-Dist: pydantic
Requires-Dist: pyyaml
Requires-Dist: requests
Requires-Dist: typing-extensions>=4.4.0
Requires-Dist: watchdog>=3.0.0
Requires-Dist: plum-dispatch<2.0.0; python_version < "3.10"
Requires-Dist: plum-dispatch>2.0.0; python_version >= "3.10"
Provides-Extra: dev
Requires-Dist: pytest<8.0.0; extra == "dev"
Requires-Dist: pytest-cov; extra == "dev"
Requires-Dist: jupyterlab; extra == "dev"
Requires-Dist: jupytext; extra == "dev"
Requires-Dist: syrupy; extra == "dev"
Requires-Dist: pre-commit; extra == "dev"
Dynamic: license-file
